eink_calendar/__init__.py
eink_calendar/__main__.py
eink_calendar/api/__init__.py
eink_calendar/api/client.py
eink_calendar/api/event.py
eink_calendar/api/event_stream.py
eink_calendar/display.py
eink_calendar/lora.ttf
eink_calendar/ui/__init__.py
eink_calendar/ui/event.py
eink_calendar/ui/text.py
eink_calendar-0.2.2.dist-info/entry_points.txt
eink_calendar-0.2.2.dist-info/LICENSE.md
eink_calendar-0.2.2.dist-info/WHEEL
eink_calendar-0.2.2.dist-info/METADATA
eink_calendar-0.2.2.dist-info/RECORD
