Metadata-Version: 2.1
Name: eink-calendar
Version: 0.2.2
Summary: Shows Google Calendar events on an Inky Impression display
Author: Tyler Compton
Author-email: xaviosx@gmail.com
Requires-Python: >=3.10,<4.0
Classifier: Programming Language :: Python :: 3
Classifier: Programming Language :: Python :: 3.10
Classifier: Programming Language :: Python :: 3.11
Requires-Dist: google-api-python-client (>=2.100.0,<3.0.0)
Requires-Dist: google-auth-httplib2 (>=0.1.1,<0.2.0)
Requires-Dist: google-auth-oauthlib (>=1.1.0,<2.0.0)
Requires-Dist: inky[example-depends,rpi] (>=1.5.0,<2.0.0)
Requires-Dist: pillow (>=10.0.1,<11.0.0)
Requires-Dist: pyxdg (>=0.28,<0.29)
